I2T2/__init__.py
I2T2/_nbdev.py
I2T2/io.py
I2T2/manipulate.py
I2T2/data/README.md
I2T2/data/__init__.py
I2T2/data/chest-xray/1-3.dcm
I2T2/data/knee/image-00000.dcm
I2T2/data/knee/image-00001.dcm
I2T2/data/knee/image-00002.dcm
I2T2/data/knee/image-00003.dcm
I2T2/data/knee/image-00004.dcm
I2T2/data/knee/image-00005.dcm
I2T2/data/knee/image-00006.dcm
I2T2/data/knee/image-00007.dcm
I2T2/data/knee/image-00008.dcm
I2T2/data/knee/image-00009.dcm
I2T2/data/knee/image-00010.dcm
I2T2/data/knee/image-00011.dcm
I2T2/data/knee/image-00012.dcm
I2T2/data/knee/image-00013.dcm
I2T2/data/knee/image-00014.dcm
I2T2/data/knee/image-00015.dcm
I2T2/data/knee/image-00016.dcm
I2T2/data/knee/image-00017.dcm
I2T2/data/knee/image-00018.dcm
I2T2/data/knee/image-00019.dcm
I2T2/data/knee/image-00020.dcm
I2T2/data/knee/image-00021.dcm
I2T2/data/knee-segmentation/knee_segmentation.h5
data/__init__.py
data/chest-xray/1-3.dcm
I2T2-0.1.7.dist-info/LICENSE
I2T2-0.1.7.dist-info/METADATA
I2T2-0.1.7.dist-info/WHEEL
I2T2-0.1.7.dist-info/entry_points.txt
I2T2-0.1.7.dist-info/top_level.txt
I2T2-0.1.7.dist-info/RECORD
