Metadata-Version: 2.1
Name: I2T2
Version: 0.1.7
Summary: Suite of useful tools for manipulating medical images.
Home-page: https://github.com/UCSF-intelligent-imaging/I2T2/tree/master/
Author: Pablo F. Damasceno
Author-email: pablo.damasceno@ucsf.edu
License: Apache Software License 2.0
Keywords: DICOM,AI,medical
Platform: UNKNOWN
Classifier: Development Status :: 3 - Alpha
Classifier: Intended Audience :: Developers
Classifier: License :: OSI Approved :: Apache Software License
Classifier: Natural Language :: English
Classifier: Programming Language :: Python :: 3.6
Classifier: Programming Language :: Python :: 3.7
Classifier: Programming Language :: Python :: 3.8
Requires-Python: >=3.6
Requires-Dist: fastscript (>=0.1.*)
Requires-Dist: ipykernel (>=5.2.*)
Requires-Dist: ipython (>=7.13.*)
Requires-Dist: jupyter (>=1.0.*)
Requires-Dist: jupyterlab (>=2.0.*)
Requires-Dist: matplotlib (>=3.2.*)
Requires-Dist: nbdev (>=0.2.*)
Requires-Dist: numpy (>=1.18.*)
Requires-Dist: pandas (>=1.0.*)
Requires-Dist: pillow (>=7.1.*)
Requires-Dist: pydicom (>=1.4.*)
Requires-Dist: pypi (>=2.1)
Requires-Dist: twine (>=3.1.*)
Requires-Dist: scipy (>=1.4.*)
Requires-Dist: h5py (>=2.10.*)
